pyincore_data/__init__.py
pyincore_data/censusutil.py
pyincore_data/censusviz.py
pyincore_data/config.py
pyincore_data/globals.py
pyincore_data/logging.ini
pyincore_data/nsibuildinginventory.py
pyincore_data/nsiparser.py
pyincore_data/utils/__init__.py
pyincore_data/utils/datautil.py
pyincore_data/utils/nsiutil.py
pyincore_data/utils/data/nsi/occ_bldg_mapping/fips_region_mapping.csv
pyincore_data/utils/data/nsi/occ_bldg_mapping/eastcoast/HighRise.csv
pyincore_data/utils/data/nsi/occ_bldg_mapping/eastcoast/LowRise.csv
pyincore_data/utils/data/nsi/occ_bldg_mapping/eastcoast/MidRise.csv
pyincore_data/utils/data/nsi/occ_bldg_mapping/midwest/HighRise.csv
pyincore_data/utils/data/nsi/occ_bldg_mapping/midwest/LowRise.csv
pyincore_data/utils/data/nsi/occ_bldg_mapping/midwest/MidRise.csv
pyincore_data/utils/data/nsi/occ_bldg_mapping/westcoast/HighRise-1950-1970.csv
pyincore_data/utils/data/nsi/occ_bldg_mapping/westcoast/HighRise-Post1970.csv
pyincore_data/utils/data/nsi/occ_bldg_mapping/westcoast/HighRise-Pre1950.csv
pyincore_data/utils/data/nsi/occ_bldg_mapping/westcoast/LowRise-1950-1970.csv
pyincore_data/utils/data/nsi/occ_bldg_mapping/westcoast/LowRise-Post1970.csv
pyincore_data/utils/data/nsi/occ_bldg_mapping/westcoast/LowRise-Pre1950.csv
pyincore_data/utils/data/nsi/occ_bldg_mapping/westcoast/MidRise-1950-1970.csv
pyincore_data/utils/data/nsi/occ_bldg_mapping/westcoast/MidRise-Post1970.csv
pyincore_data/utils/data/nsi/occ_bldg_mapping/westcoast/MidRise-Pre1950.csv
pyincore_data-1.0.0.dist-info/licenses/LICENSE
pyincore_data-1.0.0.dist-info/METADATA
pyincore_data-1.0.0.dist-info/WHEEL
pyincore_data-1.0.0.dist-info/top_level.txt
pyincore_data-1.0.0.dist-info/RECORD
